xyz_tools_plus/__init__.py
xyz_tools_plus/AI/AI.py
xyz_tools_plus/AI/__init__.py
xyz_tools_plus/RSA/RSA.py
xyz_tools_plus/RSA/__init__.py
xyz_tools_plus/_hash/__init__.py
xyz_tools_plus/_hash/hash.py
xyz_tools_plus/_random/__init__.py
xyz_tools_plus/_random/random.py
xyz_tools_plus/math/__init__.py
xyz_tools_plus/math/math.py
xyz_tools_plus/mod/__init__.py
xyz_tools_plus/mod/mod.py
xyz_tools_plus/morse/__init__.py
xyz_tools_plus/morse/morse.py
xyz_tools_plus/puzzle/__init__.py
xyz_tools_plus/puzzle/puzzle.py
xyz_tools_plus/sort/__init__.py
xyz_tools_plus/sort/sort.py
xyz_tools_plus-0.1.6.dist-info/METADATA
xyz_tools_plus-0.1.6.dist-info/WHEEL
xyz_tools_plus-0.1.6.dist-info/top_level.txt
xyz_tools_plus-0.1.6.dist-info/RECORD
