Metadata-Version: 2.2
Name: xyz-tools-plus
Version: 0.1.6
Summary: 一个用于多功能的Python库
Author: mly, wyy, sty
Classifier: Programming Language :: Python :: 3
Classifier: License :: OSI Approved :: MIT License
Classifier: Operating System :: OS Independent
Requires-Python: >=3.12
Dynamic: author
Dynamic: classifier
Dynamic: description
Dynamic: description-content-type
Dynamic: requires-python
Dynamic: summary
